blossomai/__init__.py
blossomai/__main__.py
blossomai/blossomai.py
blossomai/cli.py
blossomai-0.1.0.dist-info/LICENSE
blossomai-0.1.0.dist-info/METADATA
blossomai-0.1.0.dist-info/WHEEL
blossomai-0.1.0.dist-info/entry_points.txt
blossomai-0.1.0.dist-info/top_level.txt
blossomai-0.1.0.dist-info/RECORD
