Metadata-Version: 2.1
Name: blossomai
Version: 0.1.0
Summary: blossomAI automates data exploration and visualization
Home-page: https://github.com/sheriftawfikabbas/blossomai
Author: Sherif Abdulkader Tawfik Abbas
Author-email: sherif.tawfic@gmail.com
License: mit
Keywords: ai,data visualization,data science
License-File: LICENSE
Requires-Dist: xgboost
Requires-Dist: pandas
Requires-Dist: numpy
